debugpy_run.py
debugpy_run-1.16.dist-info/METADATA
debugpy_run-1.16.dist-info/WHEEL
debugpy_run-1.16.dist-info/entry_points.txt
debugpy_run-1.16.dist-info/top_level.txt
debugpy_run-1.16.dist-info/RECORD
