Metadata-Version: 2.4
Name: debugpy-run
Version: 1.16
Summary: Finds and runs debugpy for VS Code "remote attach" command line debugging
Author-email: Mark Blakeney <mark.blakeney@bullet-systems.net>
License-Expression: GPL-3.0-or-later
Project-URL: Homepage, https://github.com/bulletmark/debugpy-run
Keywords: debugpy,vscode,code,ptvsd
Classifier: Programming Language :: Python :: 3
Requires-Python: >=3.6
Requires-Dist: packaging
Requires-Dist: debugpy
Requires-Dist: psutil
